wink_sdk_channel_manager/__init__.py
wink_sdk_channel_manager/api_client.py
wink_sdk_channel_manager/api_response.py
wink_sdk_channel_manager/configuration.py
wink_sdk_channel_manager/exceptions.py
wink_sdk_channel_manager/py.typed
wink_sdk_channel_manager/rest.py
wink_sdk_channel_manager/api/__init__.py
wink_sdk_channel_manager/api/channel_manager_api.py
wink_sdk_channel_manager/models/__init__.py
wink_sdk_channel_manager/models/channel_manager_property.py
wink_sdk_channel_manager/models/custom_monetary_amount.py
wink_sdk_channel_manager/models/generic_error_message.py
wink_sdk_channel_manager/models/model_property.py
wink_sdk_channel_manager/models/page_channel_manager_property.py
wink_sdk_channel_manager/models/page_property.py
wink_sdk_channel_manager/models/pageable_object.py
wink_sdk_channel_manager/models/ping_response.py
wink_sdk_channel_manager/models/property_booking.py
wink_sdk_channel_manager/models/property_rate.py
wink_sdk_channel_manager/models/property_rate_update_request.py
wink_sdk_channel_manager/models/property_room_rate.py
wink_sdk_channel_manager/models/property_room_rate_with_rate_list.py
wink_sdk_channel_manager/models/property_with_room_rate_list.py
wink_sdk_channel_manager/models/show_property_room_rates400_response.py
wink_sdk_channel_manager/models/sort_object.py
wink_sdk_channel_manager/models/variable_charge.py
wink_sdk_channel_manager-0.0.57.dist-info/licenses/LICENSE
wink_sdk_channel_manager-0.0.57.dist-info/METADATA
wink_sdk_channel_manager-0.0.57.dist-info/WHEEL
wink_sdk_channel_manager-0.0.57.dist-info/top_level.txt
wink_sdk_channel_manager-0.0.57.dist-info/RECORD
